{
    "Amazon RDS for MySQL": [
        {
            "GDP version": "11.3.0",
            "GI version": "",
            "Data source": "Amazon RDS for MySQL",
            "Data source version": "5.7+",
            "VA supported": "yes",
            "Classification supported": "yes",
            "Notes": "Classification via GDP",
            "Download URL": "https://github.com/IBM/universal-connectors/releases/download/v1.2.0/MysqlOverCloudwatchLogsPackage.zip",
            "Readme URL": "https://github.com/IBM/universal-connectors/blob/main/filter-plugin/logstash-filter-dynamodb-guardium/README.md"
        },
        {
            "GDP version": "",
            "GI version": "3.2.0 - 3.3.0",
            "Data source": "Amazon RDS for MySQL",
            "Data source version": "5.7+",
            "VA supported": "yes",
            "Classification supported": "yes",
            "Notes": "Classification via GDP",
            "Download URL": "https://github.com/IBM/universal-connectors/releases/download/v1.2.0/MysqlOverCloudwatchLogsPackage.zip",
            "Readme URL": ""
        },
        {
            "GDP version": "11.4.0 - 11.5.0",
            "GI version": "",
            "Data source": "Amazon RDS for MySQL",
            "Data source version": "5.7+",
            "VA supported": "yes",
            "Classification supported": "yes",
            "Notes": "Classification via GDP",
            "Download URL": "https://github.com/IBM/universal-connectors/releases/download/v1.2.0/MysqlOverCloudwatchLogsPackage.zip",
            "Readme URL": ""
        },
        {
            "GDP version": "12.0.0",
            "GI version": "",
            "Data source": "Amazon RDS for MySQL",
            "Data source version": "5.7+",
            "VA supported": "yes",
            "Classification supported": "yes",
            "Notes": "Classification via GDP",
            "Download URL": "https://github.com/IBM/universal-connectors/releases/download/v1.2.0/MysqlOverCloudwatchLogsPackage.zip",
            "Readme URL": "https://github.com/IBM/universal-connectors/blob/main/filter-plugin/logstash-filter-oua-guardium/README.md"
        },
        {
            "GDP version": "",
            "GI version": "saas",
            "Data source": "Amazon RDS for MySQL",
            "Data source version": "5.7+",
            "VA supported": "yes",
            "Classification supported": "yes",
            "Notes": "Classification via GDP",
            "Download URL": "https://github.com/IBM/universal-connectors/releases/download/v1.2.0/MysqlOverCloudwatchLogsPackage.zip",
            "Readme URL": "https://github.com/IBM/universal-connectors/blob/main/filter-plugin/logstash-filter-documentdb-aws-guardium/README.md"
        }
    ],
    "Amazon Redshift": [
        {
            "GDP version": "11.3.0",
            "GI version": "",
            "Data source": "Amazon Redshift",
            "Data source version": "1.0.40182",
            "VA supported": "yes",
            "Classification supported": "yes",
            "Notes": "Classification via GDP and ISDC",
            "Download URL": "",
            "Readme URL": "https://github.com/IBM/universal-connectors/blob/main/filter-plugin/logstash-filter-mariadb-aws-guardium/README.md"
        },
        {
            "GDP version": "11.4.0",
            "GI version": "",
            "Data source": "Amazon Redshift",
            "Data source version": "1.0.40182",
            "VA supported": "yes",
            "Classification supported": "yes",
            "Notes": "Classification via GDP and ISDC",
            "Download URL": "",
            "Readme URL": "https://github.com/IBM/universal-connectors/blob/main/filter-plugin/logstash-filter-postgres-guardium/README.md"
        },
        {
            "GDP version": "11.5.0 - 12.0.0",
            "GI version": "",
            "Data source": "Amazon Redshift",
            "Data source version": "1.0.40182",
            "VA supported": "yes",
            "Classification supported": "yes",
            "Notes": "Classification via GDP and ISDC",
            "Download URL": "",
            "Readme URL": ""
        }
    ],
    "Amazon RDS for PostgreSQL": [
        {
            "GDP version": "11.3.0",
            "GI version": "",
            "Data source": "Amazon RDS for PostgreSQL",
            "Data source version": "10.0+",
            "VA supported": "yes",
            "Classification supported": "yes",
            "Notes": "Classification via GDP",
            "Download URL": "https://github.com/IBM/universal-connectors/releases/download/v1.2.0/PostgresOverCloudWatchPackage.zip",
            "Readme URL": "https://github.com/IBM/universal-connectors/blob/main/filter-plugin/logstash-filter-mariadb-aws-guardium/README.md"
        },
        {
            "GDP version": "",
            "GI version": "3.3.0 - saas",
            "Data source": "Amazon RDS for PostgreSQL",
            "Data source version": "10.0+",
            "VA supported": "yes",
            "Classification supported": "yes",
            "Notes": "Classification via GDP",
            "Download URL": "https://github.com/IBM/universal-connectors/releases/download/v1.2.0/PostgresOverCloudWatchPackage.zip",
            "Readme URL": ""
        },
        {
            "GDP version": "11.4.0 - 12.0.0",
            "GI version": "",
            "Data source": "Amazon RDS for PostgreSQL",
            "Data source version": "10.0+",
            "VA supported": "yes",
            "Classification supported": "yes",
            "Notes": "Classification via GDP",
            "Download URL": "https://github.com/IBM/universal-connectors/releases/download/v1.2.0/PostgresOverCloudWatchPackage.zip",
            "Readme URL": ""
        },
        {
            "GDP version": "11.5.0",
            "GI version": "",
            "Data source": "Amazon RDS for PostgreSQL",
            "Data source version": "10.0+",
            "VA supported": "yes",
            "Classification supported": "yes",
            "Notes": "Classification via GDP",
            "Download URL": "https://github.com/IBM/universal-connectors/releases/download/v1.2.0/PostgresOverCloudWatchPackage.zip",
            "Readme URL": "https://github.com/IBM/universal-connectors/blob/main/filter-plugin/logstash-filter-dynamodb-guardium/README.md"
        },
        {
            "GDP version": "",
            "GI version": "3.2.0",
            "Data source": "Amazon RDS for PostgreSQL",
            "Data source version": "10.0+",
            "VA supported": "yes",
            "Classification supported": "yes",
            "Notes": "Classification via GDP",
            "Download URL": "https://github.com/IBM/universal-connectors/releases/download/v1.2.0/PostgresOverCloudWatchPackage.zip",
            "Readme URL": "https://github.com/IBM/universal-connectors/blob/main/filter-plugin/logstash-filter-aurora-mysql-guardium/README.md"
        }
    ],
    "Amazon Aurora MySQL": [
        {
            "GDP version": "11.3.0",
            "GI version": "",
            "Data source": "Amazon Aurora MySQL",
            "Data source version": "2.0+",
            "VA supported": "",
            "Classification supported": "yes",
            "Notes": "Classification via ISDC",
            "Download URL": "https://github.com/IBM/universal-connectors/raw/main/filter-plugin/logstash-filter-aurora-mysql-guardium/AuroraMysqlOverCloudwatchPackage/AuroraMysql/Aurora-Mysql-offlinePlugin.zip",
            "Readme URL": "https://github.com/IBM/universal-connectors/blob/main/filter-plugin/logstash-filter-neptune-aws-guardium/README.md"
        },
        {
            "GDP version": "11.4.0",
            "GI version": "",
            "Data source": "Amazon Aurora MySQL",
            "Data source version": "2.0+",
            "VA supported": "",
            "Classification supported": "yes",
            "Notes": "Classification via ISDC",
            "Download URL": "https://github.com/IBM/universal-connectors/raw/main/filter-plugin/logstash-filter-aurora-mysql-guardium/AuroraMysqlOverCloudwatchPackage/AuroraMysql/Aurora-Mysql-offlinePlugin.zip",
            "Readme URL": "https://github.com/IBM/universal-connectors/blob/main/filter-plugin/logstash-filter-mysql-aws-guardium/README.md"
        },
        {
            "GDP version": "11.5.0",
            "GI version": "",
            "Data source": "Amazon Aurora MySQL",
            "Data source version": "2.0+",
            "VA supported": "",
            "Classification supported": "yes",
            "Notes": "Classification via ISDC",
            "Download URL": "https://github.com/IBM/universal-connectors/raw/main/filter-plugin/logstash-filter-aurora-mysql-guardium/AuroraMysqlOverCloudwatchPackage/AuroraMysql/Aurora-Mysql-offlinePlugin.zip",
            "Readme URL": "https://github.com/IBM/universal-connectors/blob/main/filter-plugin/logstash-filter-mongodb-guardium/README.md"
        },
        {
            "GDP version": "",
            "GI version": "3.2.0 - saas",
            "Data source": "Amazon Aurora MySQL",
            "Data source version": "2.0+",
            "VA supported": "",
            "Classification supported": "yes",
            "Notes": "Classification via ISDC",
            "Download URL": "https://github.com/IBM/universal-connectors/raw/main/filter-plugin/logstash-filter-aurora-mysql-guardium/AuroraMysqlOverCloudwatchPackage/AuroraMysql/Aurora-Mysql-offlinePlugin.zip",
            "Readme URL": ""
        },
        {
            "GDP version": "12.0.0",
            "GI version": "",
            "Data source": "Amazon Aurora MySQL",
            "Data source version": "2.0+",
            "VA supported": "",
            "Classification supported": "yes",
            "Notes": "Classification via ISDC",
            "Download URL": "https://github.com/IBM/universal-connectors/raw/main/filter-plugin/logstash-filter-aurora-mysql-guardium/AuroraMysqlOverCloudwatchPackage/AuroraMysql/Aurora-Mysql-offlinePlugin.zip",
            "Readme URL": ""
        }
    ],
    "Amazon S3": [
        {
            "GDP version": "11.3.0 - 11.5.0",
            "GI version": "",
            "Data source": "Amazon S3",
            "Data source version": "latest",
            "VA supported": "",
            "Classification supported": "yes",
            "Notes": "Classification via ISDC",
            "Download URL": "https://github.com/IBM/universal-connectors/releases/download/v1.2.0/S3OverCloudwatchLogsPackage.zip",
            "Readme URL": "https://github.com/IBM/universal-connectors/blob/main/filter-plugin/logstash-filter-mariadb-aws-guardium/README.md"
        },
        {
            "GDP version": "11.4.0 - 12.0.0",
            "GI version": "",
            "Data source": "Amazon S3",
            "Data source version": "latest",
            "VA supported": "",
            "Classification supported": "yes",
            "Notes": "Classification via ISDC",
            "Download URL": "https://github.com/IBM/universal-connectors/releases/download/v1.2.0/S3OverCloudwatchLogsPackage.zip",
            "Readme URL": ""
        },
        {
            "GDP version": "",
            "GI version": "3.2.0",
            "Data source": "Amazon S3",
            "Data source version": "latest",
            "VA supported": "",
            "Classification supported": "yes",
            "Notes": "Classification via ISDC",
            "Download URL": "https://github.com/IBM/universal-connectors/releases/download/v1.2.0/S3OverCloudwatchLogsPackage.zip",
            "Readme URL": ""
        },
        {
            "GDP version": "",
            "GI version": "3.3.0",
            "Data source": "Amazon S3",
            "Data source version": "latest",
            "VA supported": "",
            "Classification supported": "yes",
            "Notes": "Classification via ISDC",
            "Download URL": "https://github.com/IBM/universal-connectors/releases/download/v1.2.0/S3OverCloudwatchLogsPackage.zip",
            "Readme URL": "https://github.com/IBM/universal-connectors/blob/main/filter-plugin/logstash-filter-mysql-aws-guardium/README.md"
        },
        {
            "GDP version": "",
            "GI version": "saas",
            "Data source": "Amazon S3",
            "Data source version": "latest",
            "VA supported": "",
            "Classification supported": "yes",
            "Notes": "Classification via ISDC",
            "Download URL": "https://github.com/IBM/universal-connectors/releases/download/v1.2.0/S3OverCloudwatchLogsPackage.zip",
            "Readme URL": "https://github.com/IBM/universal-connectors/blob/main/filter-plugin/logstash-filter-mongodb-guardium/README.md"
        }
    ],
    "Amazon DynamoDB": [
        {
            "GDP version": "11.3.0 - 12.0.0",
            "GI version": "",
            "Data source": "Amazon DynamoDB",
            "Data source version": "2019.11.21",
            "VA supported": "",
            "Classification supported": "",
            "Notes": "",
            "Download URL": "https://github.com/IBM/universal-connectors/releases/download/v1.2.0/DynamodbOverCloudwatchPackage.zip",
            "Readme URL": ""
        },
        {
            "GDP version": "",
            "GI version": "3.2.0 - saas",
            "Data source": "Amazon DynamoDB",
            "Data source version": "2019.11.21",
            "VA supported": "",
            "Classification supported": "",
            "Notes": "",
            "Download URL": "https://github.com/IBM/universal-connectors/releases/download/v1.2.0/DynamodbOverCloudwatchPackage.zip",
            "Readme URL": ""
        },
        {
            "GDP version": "",
            "GI version": "3.3.0",
            "Data source": "Amazon DynamoDB",
            "Data source version": "2019.11.21",
            "VA supported": "",
            "Classification supported": "",
            "Notes": "",
            "Download URL": "https://github.com/IBM/universal-connectors/releases/download/v1.2.0/DynamodbOverCloudwatchPackage.zip",
            "Readme URL": "https://github.com/IBM/universal-connectors/blob/main/filter-plugin/logstash-filter-mariadb-aws-guardium/README.md"
        }
    ],
    "Amazon RDS for Microsoft SQL Server": [
        {
            "GDP version": "11.3.0 - 12.0.0",
            "GI version": "",
            "Data source": "Amazon RDS for Microsoft SQL Server",
            "Data source version": "14.0.x",
            "VA supported": "yes",
            "Classification supported": "yes",
            "Notes": "Classification via GDP",
            "Download URL": "https://github.com/IBM/universal-connectors/raw/main/filter-plugin/logstash-filter-mssql-guardium/MssqlOverJdbcPackage/mssql-offline-plugins-7.5.2.zip",
            "Readme URL": ""
        },
        {
            "GDP version": "",
            "GI version": "3.3.0 (planned)",
            "Data source": "Amazon RDS for Microsoft SQL Server",
            "Data source version": "14.0.x",
            "VA supported": "yes",
            "Classification supported": "yes",
            "Notes": "Classification via GDP",
            "Download URL": "https://github.com/IBM/universal-connectors/raw/main/filter-plugin/logstash-filter-mssql-guardium/MssqlOverJdbcPackage/mssql-offline-plugins-7.5.2.zip",
            "Readme URL": "https://github.com/IBM/universal-connectors/blob/main/filter-plugin/logstash-filter-oua-guardium/README.md"
        },
        {
            "GDP version": "",
            "GI version": "saas",
            "Data source": "Amazon RDS for Microsoft SQL Server",
            "Data source version": "14.0.x",
            "VA supported": "yes",
            "Classification supported": "yes",
            "Notes": "Classification via GDP",
            "Download URL": "https://github.com/IBM/universal-connectors/raw/main/filter-plugin/logstash-filter-mssql-guardium/MssqlOverJdbcPackage/mssql-offline-plugins-7.5.2.zip",
            "Readme URL": "https://github.com/IBM/universal-connectors/blob/main/filter-plugin/logstash-filter-s3-guardium/README.md"
        }
    ],
    "MongoDB Atlas": [
        {
            "GDP version": "",
            "GI version": "3.2.0 - saas",
            "Data source": "MongoDB Atlas",
            "Data source version": "4.2",
            "VA supported": "",
            "Classification supported": "",
            "Notes": "",
            "Download URL": "https://github.com/IBM/universal-connectors/releases/download/v1.2.0/MongodbOverFilebeatPackage.zip",
            "Readme URL": ""
        },
        {
            "GDP version": "11.3.0 - 12.0.0",
            "GI version": "",
            "Data source": "MongoDB Atlas",
            "Data source version": "4.4",
            "VA supported": "",
            "Classification supported": "",
            "Notes": "",
            "Download URL": "https://github.com/IBM/universal-connectors/releases/download/v1.2.0/MongodbOverFilebeatPackage.zip",
            "Readme URL": ""
        },
        {
            "GDP version": "",
            "GI version": "3.3.0",
            "Data source": "MongoDB Atlas",
            "Data source version": "4.4",
            "VA supported": "",
            "Classification supported": "",
            "Notes": "",
            "Download URL": "https://github.com/IBM/universal-connectors/releases/download/v1.2.0/MongodbOverFilebeatPackage.zip",
            "Readme URL": ""
        },
        {
            "GDP version": "11.3.0",
            "GI version": "",
            "Data source": "MongoDB Atlas",
            "Data source version": "4.2",
            "VA supported": "",
            "Classification supported": "",
            "Notes": "",
            "Download URL": "https://github.com/IBM/universal-connectors/releases/download/v1.2.0/MongodbOverFilebeatPackage.zip",
            "Readme URL": ""
        },
        {
            "GDP version": "11.4.0",
            "GI version": "",
            "Data source": "MongoDB Atlas",
            "Data source version": "4.2",
            "VA supported": "",
            "Classification supported": "",
            "Notes": "",
            "Download URL": "https://github.com/IBM/universal-connectors/releases/download/v1.2.0/MongodbOverFilebeatPackage.zip",
            "Readme URL": "https://github.com/IBM/universal-connectors/blob/main/filter-plugin/logstash-filter-documentdb-aws-guardium/README.md"
        },
        {
            "GDP version": "11.5.0",
            "GI version": "",
            "Data source": "MongoDB Atlas",
            "Data source version": "4.2 - 4.4",
            "VA supported": "",
            "Classification supported": "",
            "Notes": "",
            "Download URL": "https://github.com/IBM/universal-connectors/releases/download/v1.2.0/MongodbOverFilebeatPackage.zip",
            "Readme URL": "https://github.com/IBM/universal-connectors/blob/main/filter-plugin/logstash-filter-mariadb-aws-guardium/README.md"
        },
        {
            "GDP version": "",
            "GI version": "3.2.0",
            "Data source": "MongoDB Atlas",
            "Data source version": "4.4",
            "VA supported": "",
            "Classification supported": "",
            "Notes": "",
            "Download URL": "https://github.com/IBM/universal-connectors/releases/download/v1.2.0/MongodbOverFilebeatPackage.zip",
            "Readme URL": "https://github.com/IBM/universal-connectors/blob/main/filter-plugin/logstash-filter-postgres-guardium/README.md"
        },
        {
            "GDP version": "12.0.0",
            "GI version": "",
            "Data source": "MongoDB Atlas",
            "Data source version": "4.2",
            "VA supported": "",
            "Classification supported": "",
            "Notes": "",
            "Download URL": "https://github.com/IBM/universal-connectors/releases/download/v1.2.0/MongodbOverFilebeatPackage.zip",
            "Readme URL": "https://github.com/IBM/universal-connectors/blob/main/filter-plugin/logstash-filter-postgres-guardium/README.md"
        },
        {
            "GDP version": "",
            "GI version": "saas",
            "Data source": "MongoDB Atlas",
            "Data source version": "4.4",
            "VA supported": "",
            "Classification supported": "",
            "Notes": "",
            "Download URL": "https://github.com/IBM/universal-connectors/releases/download/v1.2.0/MongodbOverFilebeatPackage.zip",
            "Readme URL": "https://github.com/IBM/universal-connectors/blob/main/filter-plugin/logstash-filter-neptune-aws-guardium/README.md"
        }
    ],
    "Amazon RDS for Oracle": [
        {
            "GDP version": "11.4.0 - 12.0.0",
            "GI version": "",
            "Data source": "Amazon RDS for Oracle",
            "Data source version": "19",
            "VA supported": "yes",
            "Classification supported": "yes",
            "Notes": "Classification via GDP",
            "Download URL": "https://github.com/IBM/universal-connectors/raw/main/filter-plugin/logstash-filter-oua-guardium/OracleUnifiedAuditPackage/OracleUnifiedAudit/guardium-oua-uc.zip",
            "Readme URL": ""
        },
        {
            "GDP version": "",
            "GI version": "3.2.0 - 3.3.0",
            "Data source": "Amazon RDS for Oracle",
            "Data source version": "19",
            "VA supported": "yes",
            "Classification supported": "yes",
            "Notes": "Classification via GDP",
            "Download URL": "https://github.com/IBM/universal-connectors/raw/main/filter-plugin/logstash-filter-oua-guardium/OracleUnifiedAuditPackage/OracleUnifiedAudit/guardium-oua-uc.zip",
            "Readme URL": ""
        },
        {
            "GDP version": "",
            "GI version": "3.3.0 - saas",
            "Data source": "Amazon RDS for Oracle",
            "Data source version": "18",
            "VA supported": "yes",
            "Classification supported": "yes",
            "Notes": "Classification via GDP",
            "Download URL": "https://github.com/IBM/universal-connectors/raw/main/filter-plugin/logstash-filter-oua-guardium/OracleUnifiedAuditPackage/OracleUnifiedAudit/guardium-oua-uc.zip",
            "Readme URL": ""
        },
        {
            "GDP version": "11.3.0 - 11.4.0",
            "GI version": "",
            "Data source": "Amazon RDS for Oracle",
            "Data source version": "18",
            "VA supported": "yes",
            "Classification supported": "yes",
            "Notes": "Classification via GDP",
            "Download URL": "https://github.com/IBM/universal-connectors/raw/main/filter-plugin/logstash-filter-oua-guardium/OracleUnifiedAuditPackage/OracleUnifiedAudit/guardium-oua-uc.zip",
            "Readme URL": ""
        },
        {
            "GDP version": "12.0.0",
            "GI version": "",
            "Data source": "Amazon RDS for Oracle",
            "Data source version": "18",
            "VA supported": "yes",
            "Classification supported": "yes",
            "Notes": "Classification via GDP",
            "Download URL": "https://github.com/IBM/universal-connectors/raw/main/filter-plugin/logstash-filter-oua-guardium/OracleUnifiedAuditPackage/OracleUnifiedAudit/guardium-oua-uc.zip",
            "Readme URL": ""
        },
        {
            "GDP version": "11.3.0",
            "GI version": "",
            "Data source": "Amazon RDS for Oracle",
            "Data source version": "19",
            "VA supported": "yes",
            "Classification supported": "yes",
            "Notes": "Classification via GDP",
            "Download URL": "https://github.com/IBM/universal-connectors/raw/main/filter-plugin/logstash-filter-oua-guardium/OracleUnifiedAuditPackage/OracleUnifiedAudit/guardium-oua-uc.zip",
            "Readme URL": "https://github.com/IBM/universal-connectors/blob/main/filter-plugin/logstash-filter-mariadb-aws-guardium/README.md"
        },
        {
            "GDP version": "11.5.0",
            "GI version": "",
            "Data source": "Amazon RDS for Oracle",
            "Data source version": "18",
            "VA supported": "yes",
            "Classification supported": "yes",
            "Notes": "Classification via GDP",
            "Download URL": "https://github.com/IBM/universal-connectors/raw/main/filter-plugin/logstash-filter-oua-guardium/OracleUnifiedAuditPackage/OracleUnifiedAudit/guardium-oua-uc.zip",
            "Readme URL": "https://github.com/IBM/universal-connectors/blob/main/filter-plugin/logstash-filter-postgres-guardium/README.md"
        },
        {
            "GDP version": "",
            "GI version": "3.2.0",
            "Data source": "Amazon RDS for Oracle",
            "Data source version": "18",
            "VA supported": "yes",
            "Classification supported": "yes",
            "Notes": "Classification via GDP",
            "Download URL": "https://github.com/IBM/universal-connectors/raw/main/filter-plugin/logstash-filter-oua-guardium/OracleUnifiedAuditPackage/OracleUnifiedAudit/guardium-oua-uc.zip",
            "Readme URL": "https://github.com/IBM/universal-connectors/blob/main/filter-plugin/logstash-filter-mssql-guardium/README.md"
        },
        {
            "GDP version": "",
            "GI version": "saas",
            "Data source": "Amazon RDS for Oracle",
            "Data source version": "19",
            "VA supported": "yes",
            "Classification supported": "yes",
            "Notes": "Classification via GDP",
            "Download URL": "https://github.com/IBM/universal-connectors/raw/main/filter-plugin/logstash-filter-oua-guardium/OracleUnifiedAuditPackage/OracleUnifiedAudit/guardium-oua-uc.zip",
            "Readme URL": "https://github.com/IBM/universal-connectors/blob/main/filter-plugin/logstash-filter-mongodb-guardium/README.md"
        }
    ],
    "Neptune": [
        {
            "GDP version": "",
            "GI version": "3.2.0",
            "Data source": "Neptune",
            "Data source version": "1.1+",
            "VA supported": "",
            "Classification supported": "",
            "Notes": "",
            "Download URL": "https://github.com/IBM/universal-connectors/releases/download/v1.2.0/NeptuneOverCloudWatchPackage.zip",
            "Readme URL": ""
        },
        {
            "GDP version": "11.3.0",
            "GI version": "",
            "Data source": "Neptune",
            "Data source version": "1.1+",
            "VA supported": "",
            "Classification supported": "",
            "Notes": "",
            "Download URL": "https://github.com/IBM/universal-connectors/releases/download/v1.2.0/NeptuneOverCloudWatchPackage.zip",
            "Readme URL": ""
        },
        {
            "GDP version": "11.4.0",
            "GI version": "",
            "Data source": "Neptune",
            "Data source version": "1.1+",
            "VA supported": "",
            "Classification supported": "",
            "Notes": "",
            "Download URL": "https://github.com/IBM/universal-connectors/releases/download/v1.2.0/NeptuneOverCloudWatchPackage.zip",
            "Readme URL": "https://github.com/IBM/universal-connectors/blob/main/filter-plugin/logstash-filter-mongodb-guardium/README.md"
        },
        {
            "GDP version": "11.5.0",
            "GI version": "",
            "Data source": "Neptune",
            "Data source version": "1.1+",
            "VA supported": "",
            "Classification supported": "",
            "Notes": "",
            "Download URL": "https://github.com/IBM/universal-connectors/releases/download/v1.2.0/NeptuneOverCloudWatchPackage.zip",
            "Readme URL": "https://github.com/IBM/universal-connectors/blob/main/filter-plugin/logstash-filter-mariadb-aws-guardium/README.md"
        },
        {
            "GDP version": "12.0.0",
            "GI version": "",
            "Data source": "Neptune",
            "Data source version": "1.1+",
            "VA supported": "",
            "Classification supported": "",
            "Notes": "",
            "Download URL": "https://github.com/IBM/universal-connectors/releases/download/v1.2.0/NeptuneOverCloudWatchPackage.zip",
            "Readme URL": "https://github.com/IBM/universal-connectors/blob/main/filter-plugin/logstash-filter-s3-guardium/README.md"
        },
        {
            "GDP version": "",
            "GI version": "3.3.0",
            "Data source": "Neptune",
            "Data source version": "1.1+",
            "VA supported": "",
            "Classification supported": "",
            "Notes": "",
            "Download URL": "https://github.com/IBM/universal-connectors/releases/download/v1.2.0/NeptuneOverCloudWatchPackage.zip",
            "Readme URL": "https://github.com/IBM/universal-connectors/blob/main/filter-plugin/logstash-filter-oua-guardium/README.md"
        },
        {
            "GDP version": "",
            "GI version": "saas",
            "Data source": "Neptune",
            "Data source version": "1.1+",
            "VA supported": "",
            "Classification supported": "",
            "Notes": "",
            "Download URL": "https://github.com/IBM/universal-connectors/releases/download/v1.2.0/NeptuneOverCloudWatchPackage.zip",
            "Readme URL": "https://github.com/infoinsights/guardium-snowflake-uc-filter"
        }
    ],
    "DocumentDB": [
        {
            "GDP version": "11.3.0 - 11.5.0",
            "GI version": "",
            "Data source": "DocumentDB",
            "Data source version": "4.0+",
            "VA supported": "",
            "Classification supported": "",
            "Notes": "",
            "Download URL": "https://github.com/IBM/universal-connectors/releases/download/v1.2.0/DocumentDBOverCloudwatchPackage.zip",
            "Readme URL": "https://github.com/IBM/universal-connectors/blob/main/filter-plugin/logstash-filter-mariadb-aws-guardium/README.md"
        },
        {
            "GDP version": "11.4.0",
            "GI version": "",
            "Data source": "DocumentDB",
            "Data source version": "4.0+",
            "VA supported": "",
            "Classification supported": "",
            "Notes": "",
            "Download URL": "https://github.com/IBM/universal-connectors/releases/download/v1.2.0/DocumentDBOverCloudwatchPackage.zip",
            "Readme URL": "https://github.com/IBM/universal-connectors/blob/main/filter-plugin/logstash-filter-s3-guardium/README.md"
        },
        {
            "GDP version": "",
            "GI version": "3.2.0 - saas",
            "Data source": "DocumentDB",
            "Data source version": "4.0+",
            "VA supported": "",
            "Classification supported": "",
            "Notes": "",
            "Download URL": "https://github.com/IBM/universal-connectors/releases/download/v1.2.0/DocumentDBOverCloudwatchPackage.zip",
            "Readme URL": ""
        },
        {
            "GDP version": "12.0.0",
            "GI version": "",
            "Data source": "DocumentDB",
            "Data source version": "4.0+",
            "VA supported": "",
            "Classification supported": "",
            "Notes": "",
            "Download URL": "https://github.com/IBM/universal-connectors/releases/download/v1.2.0/DocumentDBOverCloudwatchPackage.zip",
            "Readme URL": ""
        }
    ],
    "Amazon RDS for MariaDB": [
        {
            "GDP version": "11.3.0",
            "GI version": "",
            "Data source": "Amazon RDS for MariaDB",
            "Data source version": "10.4",
            "VA supported": "",
            "Classification supported": "",
            "Notes": "",
            "Download URL": "https://github.com/IBM/universal-connectors/raw/main/filter-plugin/logstash-filter-mariadb-aws-guardium/MariaDBOverCloudWatchPackage/MariaDB/logstash-filter-awsmariadb_guardium_filter.zip",
            "Readme URL": "https://github.com/IBM/universal-connectors/blob/main/filter-plugin/logstash-filter-aurora-mysql-guardium/README.md"
        },
        {
            "GDP version": "11.5.0",
            "GI version": "",
            "Data source": "Amazon RDS for MariaDB",
            "Data source version": "10.7",
            "VA supported": "",
            "Classification supported": "",
            "Notes": "",
            "Download URL": "https://github.com/IBM/universal-connectors/raw/main/filter-plugin/logstash-filter-mariadb-aws-guardium/MariaDBOverCloudWatchPackage/MariaDB/logstash-filter-awsmariadb_guardium_filter.zip",
            "Readme URL": "https://github.com/IBM/universal-connectors/blob/main/filter-plugin/logstash-filter-aurora-mysql-guardium/README.md"
        },
        {
            "GDP version": "11.3.0 - 12.0.0",
            "GI version": "",
            "Data source": "Amazon RDS for MariaDB",
            "Data source version": "10.6",
            "VA supported": "",
            "Classification supported": "",
            "Notes": "",
            "Download URL": "https://github.com/IBM/universal-connectors/raw/main/filter-plugin/logstash-filter-mariadb-aws-guardium/MariaDBOverCloudWatchPackage/MariaDB/logstash-filter-awsmariadb_guardium_filter.zip",
            "Readme URL": ""
        },
        {
            "GDP version": "",
            "GI version": "saas",
            "Data source": "Amazon RDS for MariaDB",
            "Data source version": "10.4 - 10.6",
            "VA supported": "",
            "Classification supported": "",
            "Notes": "",
            "Download URL": "https://github.com/IBM/universal-connectors/raw/main/filter-plugin/logstash-filter-mariadb-aws-guardium/MariaDBOverCloudWatchPackage/MariaDB/logstash-filter-awsmariadb_guardium_filter.zip",
            "Readme URL": ""
        },
        {
            "GDP version": "",
            "GI version": "3.2.0",
            "Data source": "Amazon RDS for MariaDB",
            "Data source version": "10.5 - 10.6",
            "VA supported": "",
            "Classification supported": "",
            "Notes": "",
            "Download URL": "https://github.com/IBM/universal-connectors/raw/main/filter-plugin/logstash-filter-mariadb-aws-guardium/MariaDBOverCloudWatchPackage/MariaDB/logstash-filter-awsmariadb_guardium_filter.zip",
            "Readme URL": ""
        },
        {
            "GDP version": "11.4.0 - 11.5.0",
            "GI version": "",
            "Data source": "Amazon RDS for MariaDB",
            "Data source version": "10.8",
            "VA supported": "",
            "Classification supported": "",
            "Notes": "",
            "Download URL": "https://github.com/IBM/universal-connectors/raw/main/filter-plugin/logstash-filter-mariadb-aws-guardium/MariaDBOverCloudWatchPackage/MariaDB/logstash-filter-awsmariadb_guardium_filter.zip",
            "Readme URL": ""
        },
        {
            "GDP version": "",
            "GI version": "3.3.0",
            "Data source": "Amazon RDS for MariaDB",
            "Data source version": "10.7",
            "VA supported": "",
            "Classification supported": "",
            "Notes": "",
            "Download URL": "https://github.com/IBM/universal-connectors/raw/main/filter-plugin/logstash-filter-mariadb-aws-guardium/MariaDBOverCloudWatchPackage/MariaDB/logstash-filter-awsmariadb_guardium_filter.zip",
            "Readme URL": ""
        },
        {
            "GDP version": "",
            "GI version": "saas",
            "Data source": "Amazon RDS for MariaDB",
            "Data source version": "10.8",
            "VA supported": "",
            "Classification supported": "",
            "Notes": "",
            "Download URL": "https://github.com/IBM/universal-connectors/raw/main/filter-plugin/logstash-filter-mariadb-aws-guardium/MariaDBOverCloudWatchPackage/MariaDB/logstash-filter-awsmariadb_guardium_filter.zip",
            "Readme URL": ""
        },
        {
            "GDP version": "11.3.0",
            "GI version": "",
            "Data source": "Amazon RDS for MariaDB",
            "Data source version": "10.5",
            "VA supported": "",
            "Classification supported": "",
            "Notes": "",
            "Download URL": "https://github.com/IBM/universal-connectors/raw/main/filter-plugin/logstash-filter-mariadb-aws-guardium/MariaDBOverCloudWatchPackage/MariaDB/logstash-filter-awsmariadb_guardium_filter.zip",
            "Readme URL": ""
        },
        {
            "GDP version": "11.3.0",
            "GI version": "",
            "Data source": "Amazon RDS for MariaDB",
            "Data source version": "10.7",
            "VA supported": "",
            "Classification supported": "",
            "Notes": "",
            "Download URL": "https://github.com/IBM/universal-connectors/raw/main/filter-plugin/logstash-filter-mariadb-aws-guardium/MariaDBOverCloudWatchPackage/MariaDB/logstash-filter-awsmariadb_guardium_filter.zip",
            "Readme URL": ""
        },
        {
            "GDP version": "11.4.0",
            "GI version": "",
            "Data source": "Amazon RDS for MariaDB",
            "Data source version": "10.4",
            "VA supported": "",
            "Classification supported": "",
            "Notes": "",
            "Download URL": "https://github.com/IBM/universal-connectors/raw/main/filter-plugin/logstash-filter-mariadb-aws-guardium/MariaDBOverCloudWatchPackage/MariaDB/logstash-filter-awsmariadb_guardium_filter.zip",
            "Readme URL": ""
        },
        {
            "GDP version": "12.0.0",
            "GI version": "",
            "Data source": "Amazon RDS for MariaDB",
            "Data source version": "10.5",
            "VA supported": "",
            "Classification supported": "",
            "Notes": "",
            "Download URL": "https://github.com/IBM/universal-connectors/raw/main/filter-plugin/logstash-filter-mariadb-aws-guardium/MariaDBOverCloudWatchPackage/MariaDB/logstash-filter-awsmariadb_guardium_filter.zip",
            "Readme URL": ""
        },
        {
            "GDP version": "12.0.0",
            "GI version": "",
            "Data source": "Amazon RDS for MariaDB",
            "Data source version": "10.7",
            "VA supported": "",
            "Classification supported": "",
            "Notes": "",
            "Download URL": "https://github.com/IBM/universal-connectors/raw/main/filter-plugin/logstash-filter-mariadb-aws-guardium/MariaDBOverCloudWatchPackage/MariaDB/logstash-filter-awsmariadb_guardium_filter.zip",
            "Readme URL": ""
        },
        {
            "GDP version": "",
            "GI version": "saas",
            "Data source": "Amazon RDS for MariaDB",
            "Data source version": "10.7",
            "VA supported": "",
            "Classification supported": "",
            "Notes": "",
            "Download URL": "https://github.com/IBM/universal-connectors/raw/main/filter-plugin/logstash-filter-mariadb-aws-guardium/MariaDBOverCloudWatchPackage/MariaDB/logstash-filter-awsmariadb_guardium_filter.zip",
            "Readme URL": "https://github.com/IBM/universal-connectors/blob/main/filter-plugin/logstash-filter-postgres-guardium/README.md"
        },
        {
            "GDP version": "11.3.0",
            "GI version": "",
            "Data source": "Amazon RDS for MariaDB",
            "Data source version": "10.8",
            "VA supported": "",
            "Classification supported": "",
            "Notes": "",
            "Download URL": "https://github.com/IBM/universal-connectors/raw/main/filter-plugin/logstash-filter-mariadb-aws-guardium/MariaDBOverCloudWatchPackage/MariaDB/logstash-filter-awsmariadb_guardium_filter.zip",
            "Readme URL": "https://github.com/IBM/universal-connectors/blob/main/filter-plugin/logstash-filter-postgres-guardium/README.md"
        },
        {
            "GDP version": "11.4.0",
            "GI version": "",
            "Data source": "Amazon RDS for MariaDB",
            "Data source version": "10.5 - 10.7",
            "VA supported": "",
            "Classification supported": "",
            "Notes": "",
            "Download URL": "https://github.com/IBM/universal-connectors/raw/main/filter-plugin/logstash-filter-mariadb-aws-guardium/MariaDBOverCloudWatchPackage/MariaDB/logstash-filter-awsmariadb_guardium_filter.zip",
            "Readme URL": "https://github.com/IBM/universal-connectors/blob/main/filter-plugin/logstash-filter-oua-guardium/README.md"
        },
        {
            "GDP version": "12.0.0",
            "GI version": "",
            "Data source": "Amazon RDS for MariaDB",
            "Data source version": "10.8",
            "VA supported": "",
            "Classification supported": "",
            "Notes": "",
            "Download URL": "https://github.com/IBM/universal-connectors/raw/main/filter-plugin/logstash-filter-mariadb-aws-guardium/MariaDBOverCloudWatchPackage/MariaDB/logstash-filter-awsmariadb_guardium_filter.zip",
            "Readme URL": "https://github.com/IBM/universal-connectors/blob/main/filter-plugin/logstash-filter-oua-guardium/README.md"
        },
        {
            "GDP version": "",
            "GI version": "3.2.0",
            "Data source": "Amazon RDS for MariaDB",
            "Data source version": "10.7",
            "VA supported": "",
            "Classification supported": "",
            "Notes": "",
            "Download URL": "https://github.com/IBM/universal-connectors/raw/main/filter-plugin/logstash-filter-mariadb-aws-guardium/MariaDBOverCloudWatchPackage/MariaDB/logstash-filter-awsmariadb_guardium_filter.zip",
            "Readme URL": "https://github.com/IBM/universal-connectors/blob/main/filter-plugin/logstash-filter-neptune-aws-guardium/README.md"
        },
        {
            "GDP version": "11.5.0",
            "GI version": "",
            "Data source": "Amazon RDS for MariaDB",
            "Data source version": "10.4",
            "VA supported": "",
            "Classification supported": "",
            "Notes": "",
            "Download URL": "https://github.com/IBM/universal-connectors/raw/main/filter-plugin/logstash-filter-mariadb-aws-guardium/MariaDBOverCloudWatchPackage/MariaDB/logstash-filter-awsmariadb_guardium_filter.zip",
            "Readme URL": "https://github.com/IBM/universal-connectors/blob/main/filter-plugin/logstash-filter-neptune-aws-guardium/README.md"
        },
        {
            "GDP version": "",
            "GI version": "3.2.0",
            "Data source": "Amazon RDS for MariaDB",
            "Data source version": "10.8",
            "VA supported": "",
            "Classification supported": "",
            "Notes": "",
            "Download URL": "https://github.com/IBM/universal-connectors/raw/main/filter-plugin/logstash-filter-mariadb-aws-guardium/MariaDBOverCloudWatchPackage/MariaDB/logstash-filter-awsmariadb_guardium_filter.zip",
            "Readme URL": "https://github.com/infoinsights/guardium-snowflake-uc-filter"
        },
        {
            "GDP version": "11.5.0",
            "GI version": "",
            "Data source": "Amazon RDS for MariaDB",
            "Data source version": "10.5",
            "VA supported": "",
            "Classification supported": "",
            "Notes": "",
            "Download URL": "https://github.com/IBM/universal-connectors/raw/main/filter-plugin/logstash-filter-mariadb-aws-guardium/MariaDBOverCloudWatchPackage/MariaDB/logstash-filter-awsmariadb_guardium_filter.zip",
            "Readme URL": "https://github.com/infoinsights/guardium-snowflake-uc-filter"
        },
        {
            "GDP version": "12.0.0",
            "GI version": "",
            "Data source": "Amazon RDS for MariaDB",
            "Data source version": "10.4",
            "VA supported": "",
            "Classification supported": "",
            "Notes": "",
            "Download URL": "https://github.com/IBM/universal-connectors/raw/main/filter-plugin/logstash-filter-mariadb-aws-guardium/MariaDBOverCloudWatchPackage/MariaDB/logstash-filter-awsmariadb_guardium_filter.zip",
            "Readme URL": "https://github.com/IBM/universal-connectors/blob/main/filter-plugin/logstash-filter-mysql-aws-guardium/README.md"
        },
        {
            "GDP version": "",
            "GI version": "3.2.0",
            "Data source": "Amazon RDS for MariaDB",
            "Data source version": "10.4",
            "VA supported": "",
            "Classification supported": "",
            "Notes": "",
            "Download URL": "https://github.com/IBM/universal-connectors/raw/main/filter-plugin/logstash-filter-mariadb-aws-guardium/MariaDBOverCloudWatchPackage/MariaDB/logstash-filter-awsmariadb_guardium_filter.zip",
            "Readme URL": "https://github.com/IBM/universal-connectors/blob/main/filter-plugin/logstash-filter-mongodb-guardium/README.md"
        },
        {
            "GDP version": "",
            "GI version": "3.3.0",
            "Data source": "Amazon RDS for MariaDB",
            "Data source version": "10.4 - 10.6",
            "VA supported": "",
            "Classification supported": "",
            "Notes": "",
            "Download URL": "https://github.com/IBM/universal-connectors/raw/main/filter-plugin/logstash-filter-mariadb-aws-guardium/MariaDBOverCloudWatchPackage/MariaDB/logstash-filter-awsmariadb_guardium_filter.zip",
            "Readme URL": "https://github.com/IBM/universal-connectors/blob/main/filter-plugin/logstash-filter-mariadb-aws-guardium/README.md"
        },
        {
            "GDP version": "",
            "GI version": "3.3.0",
            "Data source": "Amazon RDS for MariaDB",
            "Data source version": "10.8",
            "VA supported": "",
            "Classification supported": "",
            "Notes": "",
            "Download URL": "https://github.com/IBM/universal-connectors/raw/main/filter-plugin/logstash-filter-mariadb-aws-guardium/MariaDBOverCloudWatchPackage/MariaDB/logstash-filter-awsmariadb_guardium_filter.zip",
            "Readme URL": "https://github.com/IBM/universal-connectors/blob/main/filter-plugin/logstash-filter-mssql-guardium/README.md"
        }
    ],
    "Snowflake": [
        {
            "GDP version": "11.3.0 - 11.5.0",
            "GI version": "",
            "Data source": "Snowflake",
            "Data source version": "1.0+",
            "VA supported": "yes",
            "Classification supported": "",
            "Notes": "",
            "Download URL": "https://github.com/IBM/universal-connectors/releases/download/v1.4.1/SnowflakeOverJbdcPackage.zip",
            "Readme URL": ""
        },
        {
            "GDP version": "",
            "GI version": "3.3.0 - saas",
            "Data source": "Snowflake",
            "Data source version": "1.0+",
            "VA supported": "yes",
            "Classification supported": "",
            "Notes": "",
            "Download URL": "https://github.com/IBM/universal-connectors/releases/download/v1.4.1/SnowflakeOverJbdcPackage.zip",
            "Readme URL": ""
        },
        {
            "GDP version": "12.0.0",
            "GI version": "",
            "Data source": "Snowflake",
            "Data source version": "1.0+",
            "VA supported": "yes",
            "Classification supported": "",
            "Notes": "",
            "Download URL": "https://github.com/IBM/universal-connectors/releases/download/v1.4.1/SnowflakeOverJbdcPackage.zip",
            "Readme URL": "https://github.com/IBM/universal-connectors/blob/main/filter-plugin/logstash-filter-documentdb-aws-guardium/README.md"
        },
        {
            "GDP version": "",
            "GI version": "3.2.6",
            "Data source": "Snowflake",
            "Data source version": "1.0+",
            "VA supported": "yes",
            "Classification supported": "",
            "Notes": "",
            "Download URL": "https://github.com/IBM/universal-connectors/releases/download/v1.4.1/SnowflakeOverJbdcPackage.zip",
            "Readme URL": "https://github.com/IBM/universal-connectors/blob/main/filter-plugin/logstash-filter-dynamodb-guardium/README.md"
        }
    ],
    "Amazon Aurora PostgreSQL": [
        {
            "GDP version": "11.3.0",
            "GI version": "",
            "Data source": "Amazon Aurora PostgreSQL",
            "Data source version": "2.0+",
            "VA supported": "",
            "Classification supported": "yes",
            "Notes": "Classification via ISDC",
            "Download URL": "https://github.com/IBM/universal-connectors/releases/download/v1.2.0/PostgresOverCloudWatchPackage.zip",
            "Readme URL": "https://github.com/infoinsights/guardium-snowflake-uc-filter"
        },
        {
            "GDP version": "11.4.0 - 12.0.0",
            "GI version": "",
            "Data source": "Amazon Aurora PostgreSQL",
            "Data source version": "2.0+",
            "VA supported": "",
            "Classification supported": "yes",
            "Notes": "Classification via ISDC",
            "Download URL": "https://github.com/IBM/universal-connectors/releases/download/v1.2.0/PostgresOverCloudWatchPackage.zip",
            "Readme URL": ""
        },
        {
            "GDP version": "",
            "GI version": "saas",
            "Data source": "Amazon Aurora PostgreSQL",
            "Data source version": "2.0+",
            "VA supported": "",
            "Classification supported": "yes",
            "Notes": "Classification via ISDC",
            "Download URL": "https://github.com/IBM/universal-connectors/releases/download/v1.2.0/PostgresOverCloudWatchPackage.zip",
            "Readme URL": ""
        },
        {
            "GDP version": "",
            "GI version": "3.2.0",
            "Data source": "Amazon Aurora PostgreSQL",
            "Data source version": "2.0+",
            "VA supported": "",
            "Classification supported": "yes",
            "Notes": "Classification via ISDC",
            "Download URL": "https://github.com/IBM/universal-connectors/releases/download/v1.2.0/PostgresOverCloudWatchPackage.zip",
            "Readme URL": "https://github.com/IBM/universal-connectors/blob/main/filter-plugin/logstash-filter-mongodb-guardium/README.md"
        },
        {
            "GDP version": "",
            "GI version": "3.3.0",
            "Data source": "Amazon Aurora PostgreSQL",
            "Data source version": "2.0+",
            "VA supported": "",
            "Classification supported": "yes",
            "Notes": "Classification via ISDC",
            "Download URL": "https://github.com/IBM/universal-connectors/releases/download/v1.2.0/PostgresOverCloudWatchPackage.zip",
            "Readme URL": "https://github.com/IBM/universal-connectors/blob/main/filter-plugin/logstash-filter-mariadb-aws-guardium/README.md"
        }
    ]
}